ambari_lld/__init__.py
ambari_lld/cli.py
ambari_lld-0.0.2.dist-info/DESCRIPTION.rst
ambari_lld-0.0.2.dist-info/METADATA
ambari_lld-0.0.2.dist-info/RECORD
ambari_lld-0.0.2.dist-info/WHEEL
ambari_lld-0.0.2.dist-info/entry_points.txt
ambari_lld-0.0.2.dist-info/metadata.json
ambari_lld-0.0.2.dist-info/top_level.txt
