Metadata-Version: 2.0
Name: ambari-lld
Version: 0.0.2
Summary: Ambari alerts as Zabbix LLD items
Home-page: https://github.com/vide/zabbix_ambari
Author: Davide Ferrari
Author-email: vide80@gmail.com
License: GPLv2
Keywords: ambari zabbix lld
Platform: UNKNOWN
Classifier: Development Status :: 3 - Alpha
Classifier: Intended Audience :: System Administrators
Classifier: License :: OSI Approved :: GNU General Public License v2 (GPLv2)
Classifier: Topic :: System :: Monitoring
Classifier: Programming Language :: Python :: 2
Classifier: Programming Language :: Python :: 2.7
Classifier: Programming Language :: Python :: 3
Requires-Dist: requests
